[
	{
		"__TYPE__": "SharedSliceContent",
		"variation": "default",
		"primary": {
			"text_group": {
				"__TYPE__": "GroupContentType",
				"value": [
					{
						"__TYPE__": "GroupItemContent",
						"value": [
							[
								"heading",
								{
									"__TYPE__": "StructuredTextContent",
									"value": [
										{
											"type": "heading2",
											"content": {
												"text": "Unusual"
											}
										}
									]
								}
							],
							[
								"body",
								{
									"__TYPE__": "StructuredTextContent",
									"value": [
										{
											"type": "paragraph",
											"content": {
												"text": "Labore adipisicing excepteur nulla proident do. Culpa non exercitation eiusmod in laborum dolore mollit velit dolor qui duis labore voluptate consequat sit. Ut reprehenderit irure aliqua non pariatur pariatur."
											}
										}
									]
								}
							]
						]
					}
				]
			}
		},
		"items": []
	}
]